find_oracle/__init__.py
find_oracle/__main__.py
find_oracle/cache.py
find_oracle/client.py
find_oracle/enviroment.py
find_oracle/finder.py
windows_oracle_finder-2022.12.12.dist-info/LICENSE
windows_oracle_finder-2022.12.12.dist-info/METADATA
windows_oracle_finder-2022.12.12.dist-info/WHEEL
windows_oracle_finder-2022.12.12.dist-info/entry_points.txt
windows_oracle_finder-2022.12.12.dist-info/top_level.txt
windows_oracle_finder-2022.12.12.dist-info/RECORD
