Metadata-Version: 2.1
Name: windows-oracle-finder
Version: 2022.12.12
Summary: A small package for windows machines to find where the installation of oracle client resides.
Home-page: https://github.com/hargikas/windows-oracle-finder
Author: Charalampos Gkikas
Author-email: hargikas@gmail.com
License: MIT
Project-URL: Say Thanks!, https://saythanks.io/to/hargikas%40gmail.com
Project-URL: Source, https://github.com/hargikas/windows-oracle-finder/
Project-URL: Tracker, https://github.com/hargikas/windows-oracle-finder/issues
Keywords: oracle windows client instantclient
Classifier: Development Status :: 4 - Beta
Classifier: Programming Language :: Python :: 3
Classifier: License :: OSI Approved :: MIT License
Classifier: Operating System :: Microsoft :: Windows
Requires-Python: >=3
License-File: LICENSE
Requires-Dist: pefile
Requires-Dist: logzero
Requires-Dist: pywin32
